<?xml version="1.0" encoding="ISO-8859-1" ?>
<?xml-stylesheet href="xsl/overview.xsl" type="text/xsl"?>
<jcsc>
  <overview>
    <packagename>ParkFinder.src.cs310.creativeteamname.client</packagename>
    <packagecount>0</packagecount>
    <name>ParkFinder.src.cs310.creativeteamname.client</name>
    <classcount>3</classcount>
    <methodscount>9</methodscount>
    <violationscount>404</violationscount>
    <linecount>175</linecount>
    <ncsscount>92</ncsscount>
    <functionpointscount>1.7358490566037736</functionpointscount>
    <unittestclasscount>0</unittestclasscount>
    <unittestscount>0</unittestscount>
    <severitylevel>3</severitylevel>
    <worstclasses>
      <worst>
        <class>ParkFinder.src.cs310.creativeteamname.client.ParkFinder</class>
        <count>395</count>
        <author><![CDATA[]]></author>
      </worst>
      <worst>
        <class>ParkFinder.src.cs310.creativeteamname.client.GreetingServiceAsync</class>
        <count>6</count>
        <author><![CDATA[]]></author>
      </worst>
      <worst>
        <class>ParkFinder.src.cs310.creativeteamname.client.GreetingService</class>
        <count>3</count>
        <author><![CDATA[]]></author>
      </worst>
    </worstclasses>
  </overview>
</jcsc>
